afd_measures/__init__.py
afd_measures/measures.py
afd_measures/utils.py
afd_measures-1.0.0.dist-info/LICENSE
afd_measures-1.0.0.dist-info/METADATA
afd_measures-1.0.0.dist-info/WHEEL
afd_measures-1.0.0.dist-info/RECORD
