Metadata-Version: 2.1
Name: afd-measures
Version: 1.0.0
Summary: A collection of measures for Approximate Functional Dependencies in relational data.
Home-page: https://github.com/MarcelPa/AFD_comparative_study
License: MIT
Author: Marcel Parciak
Author-email: marcel.parciak@uhasselt.be
Requires-Python: >=3.9,<4.0
Classifier: Intended Audience :: Science/Research
Classifier: License :: OSI Approved :: MIT License
Classifier: Programming Language :: Python :: 3
Classifier: Programming Language :: Python :: 3.9
Classifier: Programming Language :: Python :: 3.10
Classifier: Programming Language :: Python :: 3.11
Classifier: Topic :: Scientific/Engineering
Classifier: Topic :: Scientific/Engineering :: Information Analysis
Provides-Extra: experiments
Requires-Dist: joblib (>=1.2.0,<2.0.0) ; extra == "experiments"
Requires-Dist: jupyterlab (>=3.5.0,<4.0.0) ; extra == "experiments"
Requires-Dist: numpy (>=1.23.5,<2.0.0)
Requires-Dist: pandas (>=1.5.2,<2.0.0)
Requires-Dist: plotly (>=5.13.0,<6.0.0) ; extra == "experiments"
Requires-Dist: scikit-learn (>=1.1.3,<2.0.0) ; extra == "experiments"
Requires-Dist: tqdm (>=4.64.1,<5.0.0) ; extra == "experiments"
Project-URL: Repository, https://github.com/MarcelPa/AFD_comparative_study
